uquake/__init__.py
uquake/core/__init__.py
uquake/core/coordinates.py
uquake/core/data_exchange.py
uquake/core/event.py
uquake/core/inventory.py
uquake/core/logging.py
uquake/core/stream.py
uquake/core/trace.py
uquake/core/util/__init__.py
uquake/core/util/attribute_handler.py
uquake/core/util/base.py
uquake/core/util/decorators.py
uquake/core/util/mixin.py
uquake/core/util/requests.py
uquake/core/util/tools.py
uquake/grid/__init__.py
uquake/grid/base.py
uquake/grid/extended.py
uquake/imaging/__init__.py
uquake/imaging/plot.py
uquake/imaging/stereonet.py
uquake/imaging/waveform.py
uquake/io/__init__.py
uquake/io/event/__init__.py
uquake/io/event/core.py
uquake/io/grid/__init__.py
uquake/io/grid/core.py
uquake/io/grid/nlloc.py
uquake/io/inventory/__init__.py
uquake/io/inventory/core.py
uquake/io/waveform/__init__.py
uquake/io/waveform/core.py
uquake/synthetic/__init__.py
uquake/synthetic/event.py
uquake/synthetic/inventory.py
uquake/synthetic/stream.py
uquake/waveform/__init__.py
uquake/waveform/pick.py
uquake/waveform/simple_mag.py
uquake-3.0.3.dist-info/LICENSE.txt
uquake-3.0.3.dist-info/METADATA
uquake-3.0.3.dist-info/WHEEL
uquake-3.0.3.dist-info/entry_points.txt
uquake-3.0.3.dist-info/RECORD
